[
  {"name":"이마트 성수점",     "type":"이마트","lat":37.5448,"lon":127.0645},
  {"name":"이마트 왕십리점",   "type":"이마트","lat":37.5612,"lon":127.0370},
  {"name":"이마트 마포점",     "type":"이마트","lat":37.5524,"lon":126.9541},
  {"name":"이마트 은평점",     "type":"이마트","lat":37.6369,"lon":126.9277},
  {"name":"이마트 수색점",     "type":"이마트","lat":37.5790,"lon":126.8865},
  {"name":"이마트 강동점",     "type":"이마트","lat":37.5326,"lon":127.1403},
  {"name":"이마트 천호점",     "type":"이마트","lat":37.5378,"lon":127.1247},
  {"name":"이마트 이수점",     "type":"이마트","lat":37.4841,"lon":126.9815},
  {"name":"이마트 양재점",     "type":"이마트","lat":37.4694,"lon":127.0344},
  {"name":"이마트 목동점",     "type":"이마트","lat":37.5273,"lon":126.8766},
  {"name":"이마트 도봉점",     "type":"이마트","lat":37.6493,"lon":127.0464},
  {"name":"이마트 가양점",     "type":"이마트","lat":37.5600,"lon":126.8583},
  {"name":"이마트 구로점",     "type":"이마트","lat":37.5070,"lon":126.8850},

  {"name":"롯데백화점 본점",   "type":"백화점","lat":37.5649,"lon":126.9817},
  {"name":"롯데백화점 잠실점", "type":"백화점","lat":37.5145,"lon":127.1028},
  {"name":"롯데백화점 강남점", "type":"백화점","lat":37.4997,"lon":127.0599},
  {"name":"롯데백화점 영등포점","type":"백화점","lat":37.5263,"lon":126.8981},
  {"name":"롯데백화점 노원점", "type":"백화점","lat":37.6557,"lon":127.0611},
  {"name":"롯데백화점 청량리점","type":"백화점","lat":37.5801,"lon":127.0455},
  {"name":"롯데백화점 관악점", "type":"백화점","lat":37.4789,"lon":126.9521},
  {"name":"현대백화점 압구정점","type":"백화점","lat":37.5278,"lon":127.0254},
  {"name":"현대백화점 무역센터점","type":"백화점","lat":37.5087,"lon":127.0603},
  {"name":"현대백화점 천호점", "type":"백화점","lat":37.5383,"lon":127.1248},
  {"name":"현대백화점 목동점", "type":"백화점","lat":37.5254,"lon":126.8754},
  {"name":"현대백화점 신촌점", "type":"백화점","lat":37.5556,"lon":126.9362},
  {"name":"현대백화점 미아점", "type":"백화점","lat":37.6316,"lon":127.0285},
  {"name":"현대백화점 디큐브시티","type":"백화점","lat":37.5106,"lon":126.8901},
  {"name":"신세계백화점 본점", "type":"백화점","lat":37.5595,"lon":126.9760},
  {"name":"신세계백화점 강남점","type":"백화점","lat":37.5043,"lon":127.0059},
  {"name":"신세계 타임스퀘어", "type":"백화점","lat":37.5178,"lon":126.9023},
  {"name":"갤러리아백화점 명품관","type":"백화점","lat":37.5263,"lon":127.0370},
  {"name":"AK플라자 구로점",   "type":"백화점","lat":37.5067,"lon":126.8827},
  {"name":"코엑스몰",          "type":"백화점","lat":37.5128,"lon":127.0590},
  {"name":"롯데월드몰",        "type":"백화점","lat":37.5138,"lon":127.1005},
  {"name":"IFC몰",             "type":"백화점","lat":37.5255,"lon":126.9270}
]
